@test/MyFragment.class
// class version 50.0 (50)
// access flags 0x31
public final class test/MyFragment extends android/app/Fragment  {


  // access flags 0x11
  public final test()V
   L0
    LINENUMBER 9 L0
    ALOAD 0
    GETSTATIC test/R$id.login : I
    INVOKEVIRTUAL test/MyFragment._$_findCachedViewById (I)Landroid/view/View;
    CHECKCAST android/widget/Button
   L1
    LINENUMBER 10 L1
    RETURN
   L2
    LOCALVARIABLE this Ltest/MyFragment; L0 L2 0
    MAXSTACK = 2
    MAXLOCALS = 1

  // access flags 0x1
  public <init>()V
   L0
    LINENUMBER 7 L0
    ALOAD 0
   L1
    LINENUMBER 7 L1
    INVOKESPECIAL android/app/Fragment.<init> ()V
    RETURN
   L2
    LOCALVARIABLE this Ltest/MyFragment; L0 L2 0
    MAXSTACK = 1
    MAXLOCALS = 1

  // access flags 0x1
  public _$_findCachedViewById(I)Landroid/view/View;
    ALOAD 0
    GETFIELD test/MyFragment._$_findViewCache : Ljava/util/HashMap;
    IFNONNULL L0
    ALOAD 0
    NEW java/util/HashMap
    DUP
    INVOKESPECIAL java/util/HashMap.<init> ()V
    PUTFIELD test/MyFragment._$_findViewCache : Ljava/util/HashMap;
   L0
    ALOAD 0
    GETFIELD test/MyFragment._$_findViewCache : Ljava/util/HashMap;
    ILOAD 1
    INVOKESTATIC java/lang/Integer.valueOf (I)Ljava/lang/Integer;
    INVOKEVIRTUAL java/util/HashMap.get (Ljava/lang/Object;)Ljava/lang/Object;
    CHECKCAST android/view/View
    ASTORE 2
    ALOAD 2
    IFNONNULL L1
    ALOAD 0
    INVOKEVIRTUAL test/MyFragment.getView ()Landroid/view/View;
    DUP
    IFNONNULL L2
    POP
    ACONST_NULL
    ARETURN
   L2
    ILOAD 1
    INVOKEVIRTUAL android/view/View.findViewById (I)Landroid/view/View;
    ASTORE 2
    ALOAD 0
    GETFIELD test/MyFragment._$_findViewCache : Ljava/util/HashMap;
    ILOAD 1
    INVOKESTATIC java/lang/Integer.valueOf (I)Ljava/lang/Integer;
    ALOAD 2
    INVOKEVIRTUAL java/util/HashMap.put (Ljava/lang/Object;Ljava/lang/Object;)Ljava/lang/Object;
    POP
   L1
    ALOAD 2
    ARETURN
    MAXSTACK = 3
    MAXLOCALS = 3

  // access flags 0x1
  public _$_clearFindViewByIdCache()V
    ALOAD 0
    GETFIELD test/MyFragment._$_findViewCache : Ljava/util/HashMap;
    IFNULL L0
    ALOAD 0
    GETFIELD test/MyFragment._$_findViewCache : Ljava/util/HashMap;
    INVOKEVIRTUAL java/util/HashMap.clear ()V
   L0
    RETURN
    MAXSTACK = 1
    MAXLOCALS = 1

  // access flags 0x1
  public onDestroyView()V
    ALOAD 0
    INVOKESPECIAL android/app/Fragment.onDestroyView ()V
    ALOAD 0
    INVOKEVIRTUAL test/MyFragment._$_clearFindViewByIdCache ()V
    RETURN
    MAXSTACK = 1
    MAXLOCALS = 1

  // access flags 0x2
  private Ljava/util/HashMap; _$_findViewCache

    // compiled from: simpleFragment.kt
}
